AUTHORS
CHANGELOG
CONTRIBUTING.rst
INSTALL
LICENSE
MANIFEST.in
README.rst
VERSION
setup.cfg
setup.py
piecutter/__init__.py
piecutter/exceptions.py
piecutter/resources.py
piecutter.egg-info/PKG-INFO
piecutter.egg-info/SOURCES.txt
piecutter.egg-info/dependency_links.txt
piecutter.egg-info/not-zip-safe
piecutter.egg-info/requires.txt
piecutter.egg-info/top_level.txt
piecutter/engines/__init__.py
piecutter/engines/django.py
piecutter/engines/filename.py
piecutter/engines/jinja.py
piecutter/engines/mock.py
piecutter/loaders/__init__.py
piecutter/loaders/github.py
piecutter/tests/__init__.py
piecutter/tests/github.py
piecutter/tests/resources.py
piecutter/tests/engines/__init__.py
piecutter/tests/engines/django.py
piecutter/tests/engines/filename.py
piecutter/tests/engines/jinja.py
piecutter/utils/__init__.py
piecutter/utils/files.py
piecutter/utils/sh.py