Metadata-Version: 1.1
Name: piecutter
Version: 0.1.1
Summary: Templating framework.
Home-page: https://piecutter.readthedocs.org/
Author: Rémy HUBSCHER
Author-email: hubscher.remy@gmail.com
License: BSD
Keywords: template templates template engine jinja2 django generator file generation scaffold
Platform: UNKNOWN
Classifier: Development Status :: 3 - Alpha
Classifier: Intended Audience :: Developers
Classifier: License :: OSI Approved :: BSD License
Classifier: Natural Language :: English
Classifier: Programming Language :: Python :: 2.7
Classifier: Programming Language :: Python :: 3.3
